setup.cfg
setup.py
cybercrimetracker/API_example.py
cybercrimetracker/__init__.py
cybercrimetracker/cybercrimeTrackerAPI.py
cybercrimetracker/test_api.py
cybercrimetracker.egg-info/PKG-INFO
cybercrimetracker.egg-info/SOURCES.txt
cybercrimetracker.egg-info/dependency_links.txt
cybercrimetracker.egg-info/requires.txt
cybercrimetracker.egg-info/top_level.txt