Metadata-Version: 1.1
Name: cybercrimetracker
Version: 0.0.2
Summary: (Unofficial) Python API for cybercrime-tracker
Home-page: https://github.com/PaulSec/cybercrime-tracker
Author: PaulSec
Author-email: paulwebsec@gmail.com
License: UNKNOWN
Download-URL: https://github.com/PaulSec/cybercrime-tracker/archive/0.0.2.tar.gz
Keywords: cybercrime-tracker,c2c,malwares,osint
Platform: UNKNOWN
